{
  "ruleChain": {
    "name": "Check telemetry validity",
    "type": "CORE",
    "firstRuleNodeId": null,
    "root": false,
    "debugMode": false,
    "configuration": null,
    "additionalInfo": {
      "description": "Set of instructions to check if the data of a telemetry has to be added for the first time or has to be changed if the same value is different due to error correction and it's closer to the average"
    }
  },
  "metadata": {
    "version": 60,
    "firstNodeIndex": 0,
    "nodes": [
      {
        "type": "org.thingsboard.rule.engine.metadata.TbGetRelatedAttributeNode",
        "name": "get_device-attributes-asset",
        "debugSettings": {
          "failuresEnabled": false,
          "allEnabled": false,
          "allEnabledUntil": 0
        },
        "singletonMode": false,
        "queueName": null,
        "configurationVersion": 1,
        "configuration": {
          "relationsQuery": {
            "fetchLastLevelOnly": false,
            "direction": "TO",
            "maxLevel": 1,
            "filters": [
              {
                "relationType": "Contains",
                "entityTypes": [
                  "ASSET"
                ]
              }
            ]
          },
          "dataToFetch": "ATTRIBUTES",
          "fetchTo": "METADATA",
          "dataMapping": {
            "general_weight": "general_weight",
            "general_temperature": "general_temperature",
            "general_humidity": "general_humidity",
            "general_noise": "general_noise"
          }
        },
        "additionalInfo": {
          "description": "get the server attributes from the related asset",
          "layoutX": 293,
          "layoutY": 151
        }
      },
      {
        "type": "org.thingsboard.rule.engine.flow.TbRuleChainOutputNode",
        "name": "output",
        "debugSettings": null,
        "singletonMode": false,
        "queueName": null,
        "configurationVersion": 0,
        "configuration": {
          "version": 0
        },
        "additionalInfo": {
          "description": "",
          "layoutX": 2262,
          "layoutY": 156
        }
      },
      {
        "type": "org.thingsboard.rule.engine.transform.TbTransformMsgNode",
        "name": "check_data-threshold",
        "debugSettings": {
          "failuresEnabled": false,
          "allEnabled": false,
          "allEnabledUntil": 0
        },
        "singletonMode": false,
        "queueName": null,
        "configurationVersion": 0,
        "configuration": {
          "scriptLang": "JS",
          "jsScript": "var message = []; // create a new message to incorporate\n/* define constants of threshold to verify if a data is correct */\nconst MINTEMPERATURETHRESHOLD = -20; // °C\nconst MAXTEMPERATURETHRESHOLD = 70;\nconst MINWEIGHTTHRESHOLD = 0; // kg\nconst MAXWEIGHTTHRESHOLD = 30;\nconst MINHUMIDITYTHRESHOLD = 0; // %\nconst MAXHUMIDITYTHRESHOLD = 100;\nconst MINNOISETHRESHOLD = 0; // Hz\nconst MAXNOISETHRESHOLD = 500;\n\n/* for each message check\nif it's over the threshold so as to eliminate it */\nvar check; // create a boolean variable\nfor(const singleMeasure of msg){\n    check = true;\n\n    if(\"temperature\" in singleMeasure && (singleMeasure.temperature<MINTEMPERATURETHRESHOLD || singleMeasure.temperature>MAXTEMPERATURETHRESHOLD))\n        check = false;\n    else if(\"humidity\" in singleMeasure && (singleMeasure.humidity<MINHUMIDITYTHRESHOLD || singleMeasure.humidity>MAXHUMIDITYTHRESHOLD))\n        check = false;\n    else if(\"weight\" in singleMeasure && (singleMeasure.weight<MINWEIGHTTHRESHOLD || singleMeasure.weight>MAXWEIGHTTHRESHOLD))\n        check = false;\n    else if(\"noise\" in singleMeasure && (singleMeasure.noise<MINNOISETHRESHOLD || singleMeasure.noise>MAXNOISETHRESHOLD))\n        check = false;\n        \n    if(check)\n        message.push(singleMeasure);\n}\n\nreturn {msg: message, metadata: metadata, msgType: msgType};",
          "tbelScript": "\nreturn {msg: msg, metadata: metadata, msgType: msgType};"
        },
        "additionalInfo": {
          "description": "check if the data given in the telemetry are out of the threshold given, so as to discard them immediately and report only changings.",
          "layoutX": 832,
          "layoutY": 152
        }
      },
      {
        "type": "org.thingsboard.rule.engine.transform.TbTransformMsgNode",
        "name": "format_message",
        "debugSettings": null,
        "singletonMode": false,
        "queueName": null,
        "configurationVersion": 0,
        "configuration": {
          "scriptLang": "JS",
          "jsScript": "/* tolerate if the data is a single object and \ntransform it into an array */\nvar dataArray = Array.isArray(msg) ? msg : [msg];\n\nreturn {msg: dataArray, metadata: metadata, msgType: msgType};",
          "tbelScript": "return {msg: msg, metadata: metadata, msgType: msgType};"
        },
        "additionalInfo": {
          "description": "format message and transform it into an array if it's not. It will become useful in the next steps. ",
          "layoutX": 553,
          "layoutY": 149
        }
      },
      {
        "type": "org.thingsboard.rule.engine.metadata.TbGetTelemetryNode",
        "name": "get_latest-telemetries",
        "debugSettings": {
          "failuresEnabled": false,
          "allEnabled": false,
          "allEnabledUntil": 0
        },
        "singletonMode": false,
        "queueName": null,
        "configurationVersion": 2,
        "configuration": {
          "latestTsKeyNames": [
            "weight",
            "temperature",
            "noise",
            "humidity"
          ],
          "aggregation": "NONE",
          "fetchMode": "ALL",
          "orderBy": "ASC",
          "limit": 1000,
          "useMetadataIntervalPatterns": false,
          "startIntervalPattern": "${minTimestamp}",
          "endIntervalPattern": "${maxTimestamp}",
          "startInterval": 2,
          "startIntervalTimeUnit": "DAYS",
          "endInterval": 1,
          "endIntervalTimeUnit": "MINUTES"
        },
        "additionalInfo": {
          "description": "get the latest telemetries with dynamic minimum and maximum timestamp",
          "layoutX": 1086,
          "layoutY": 153
        }
      },
      {
        "type": "org.thingsboard.rule.engine.transform.TbSplitArrayMsgNode",
        "name": "split_array-telemetries",
        "debugSettings": null,
        "singletonMode": false,
        "queueName": null,
        "configurationVersion": 0,
        "configuration": {
          "version": 0
        },
        "additionalInfo": {
          "description": "split the array of telemetries into single messages to process",
          "layoutX": 1359,
          "layoutY": 145
        }
      },
      {
        "type": "org.thingsboard.rule.engine.transform.TbTransformMsgNode",
        "name": "check_telemetry-value",
        "debugSettings": {
          "failuresEnabled": false,
          "allEnabled": false,
          "allEnabledUntil": 0
        },
        "singletonMode": false,
        "queueName": null,
        "configurationVersion": 0,
        "configuration": {
          "scriptLang": "JS",
          "jsScript": "/* variable definition */\nvar currentIndex = -1, currentKey, telemetryList, check = true, result = true;\n\ncurrentKey = Object.keys(msg)[0]; // get the first and only key\n\n/* get the list of telemetries\nand find the telemetry that match the timestamp */\nif(!(currentKey in metadata))\n    check = false;\nelse{\n    telemetryList = JSON.parse(metadata[currentKey]);\n    currentIndex = telemetryList.findIndex(singleTelemetry => Number(singleTelemetry.ts) === Number(metadata.ts));   \n}\n\n/* control if a telemetry has been found,\notherwise it's not possible to compare it with other telemetries */\nif(currentIndex<0)\n    check=false;\n\n/* control if the general average \nhas been found in the common asset */\nif(!(\"general_\"+currentKey in metadata))\n    check=false;\n    \n/* control if the message is closer to the average, otherwise\nit's not possible to replace the telemetry */\nif(Math.abs(msg[currentKey] - Number(metadata[\"general_\"+currentKey]))>=Math.abs(Number(telemetryList[currentIndex].value) - Number(metadata[\"general_\"+currentKey])))\n    result = false;\n    \n/* copy the result to metadata and\nreturn the message */\nmetadata.valid = result;\nmetadata.sameTelemetry = currentIndex;\n\nreturn {msg: msg, metadata: metadata, msgType: msgType};",
          "tbelScript": "/* variable definition */\n\nreturn {msg: msg, metadata: metadata, msgType: msgType};"
        },
        "additionalInfo": {
          "description": "node to check the value of the telemetry in order to establish if it can replace o be saved to the database",
          "layoutX": 1630,
          "layoutY": 143
        }
      },
      {
        "type": "org.thingsboard.rule.engine.filter.TbJsSwitchNode",
        "name": "switch_message-validity",
        "debugSettings": {
          "failuresEnabled": false,
          "allEnabled": false,
          "allEnabledUntil": 0
        },
        "singletonMode": false,
        "queueName": null,
        "configurationVersion": 0,
        "configuration": {
          "scriptLang": "JS",
          "jsScript": "var result = JSON.parse(metadata.valid); // add this to get the boolean\n\nif(result)\n    return ['valid'];\n\nreturn ['dropped'];",
          "tbelScript": "function nextRelation(metadata, msg) {\n    return ['one','nine'];\n}\nif(msgType == 'POST_TELEMETRY_REQUEST') {\n    return ['two'];\n}\nreturn nextRelation(metadata, msg);"
        },
        "additionalInfo": {
          "description": "switch that process the validity of the message ",
          "layoutX": 1932,
          "layoutY": 148
        }
      },
      {
        "type": "org.thingsboard.rule.engine.action.TbCreateAlarmNode",
        "name": "error_device-timeseries",
        "debugSettings": null,
        "singletonMode": false,
        "queueName": null,
        "configurationVersion": 0,
        "configuration": {
          "scriptLang": "TBEL",
          "alarmDetailsBuildJs": "var details = {};\nif (metadata.prevAlarmDetails) {\n    details = JSON.parse(metadata.prevAlarmDetails);\n    //remove prevAlarmDetails from metadata\n    delete metadata.prevAlarmDetails;\n    //now metadata is the same as it comes IN this rule node\n}\n\n\nreturn details;",
          "alarmDetailsBuildTbel": "var details = {};\nif (metadata.prevAlarmDetails != null) {\n    details = JSON.parse(metadata.prevAlarmDetails);\n    //remove prevAlarmDetails from metadata\n    metadata.remove('prevAlarmDetails');\n    //now metadata is the same as it comes IN this rule node\n}\n\n\nreturn details;",
          "useMessageAlarmData": false,
          "overwriteAlarmDetails": false,
          "alarmType": "ErrorDeviceTimeseries",
          "severity": "MINOR",
          "propagate": false,
          "relationTypes": [],
          "propagateToOwner": false,
          "propagateToTenant": false,
          "dynamicSeverity": false
        },
        "additionalInfo": {
          "description": "generate an error when it's not possible to get the timeseries of the device",
          "layoutX": 1370,
          "layoutY": 230
        }
      },
      {
        "type": "org.thingsboard.rule.engine.action.TbCreateAlarmNode",
        "name": "error_asset-attributes",
        "debugSettings": null,
        "singletonMode": false,
        "queueName": null,
        "configurationVersion": 0,
        "configuration": {
          "scriptLang": "TBEL",
          "alarmDetailsBuildJs": "var details = {};\nif (metadata.prevAlarmDetails) {\n    details = JSON.parse(metadata.prevAlarmDetails);\n    //remove prevAlarmDetails from metadata\n    delete metadata.prevAlarmDetails;\n    //now metadata is the same as it comes IN this rule node\n}\n\n\nreturn details;",
          "alarmDetailsBuildTbel": "var details = {};\nif (metadata.prevAlarmDetails != null) {\n    details = JSON.parse(metadata.prevAlarmDetails);\n    //remove prevAlarmDetails from metadata\n    metadata.remove('prevAlarmDetails');\n    //now metadata is the same as it comes IN this rule node\n}\n\n\nreturn details;",
          "useMessageAlarmData": false,
          "overwriteAlarmDetails": false,
          "alarmType": "FailedAssetAttributes",
          "severity": "MINOR",
          "propagate": false,
          "relationTypes": [],
          "propagateToOwner": false,
          "propagateToTenant": false,
          "dynamicSeverity": false
        },
        "additionalInfo": {
          "description": "error when it's not possible to get the attributes from the common asset",
          "layoutX": 562,
          "layoutY": 218
        }
      }
    ],
    "connections": [
      {
        "fromIndex": 0,
        "toIndex": 3,
        "type": "Success"
      },
      {
        "fromIndex": 0,
        "toIndex": 9,
        "type": "Failure"
      },
      {
        "fromIndex": 2,
        "toIndex": 4,
        "type": "Success"
      },
      {
        "fromIndex": 3,
        "toIndex": 2,
        "type": "Success"
      },
      {
        "fromIndex": 4,
        "toIndex": 5,
        "type": "Success"
      },
      {
        "fromIndex": 4,
        "toIndex": 8,
        "type": "Failure"
      },
      {
        "fromIndex": 5,
        "toIndex": 6,
        "type": "Success"
      },
      {
        "fromIndex": 6,
        "toIndex": 7,
        "type": "Success"
      },
      {
        "fromIndex": 7,
        "toIndex": 1,
        "type": "valid"
      }
    ],
    "ruleChainConnections": null
  }
}